odoo/addons/l10n_fr_account_tax_unece/README.rst
odoo/addons/l10n_fr_account_tax_unece/__init__.py
odoo/addons/l10n_fr_account_tax_unece/__manifest__.py
odoo/addons/l10n_fr_account_tax_unece/post_install.py
odoo/addons/l10n_fr_account_tax_unece/data/account_tax_template.xml
odoo/addons/l10n_fr_account_tax_unece/i18n/l10n_fr_account_tax_unece.pot
odoo/addons/l10n_fr_account_tax_unece/readme/CONTRIBUTORS.rst
odoo/addons/l10n_fr_account_tax_unece/readme/DESCRIPTION.rst
odoo/addons/l10n_fr_account_tax_unece/static/description/icon.png
odoo/addons/l10n_fr_account_tax_unece/static/description/index.html
odoo14_addon_l10n_fr_account_tax_unece-14.0.1.1.0.dist-info/METADATA
odoo14_addon_l10n_fr_account_tax_unece-14.0.1.1.0.dist-info/WHEEL
odoo14_addon_l10n_fr_account_tax_unece-14.0.1.1.0.dist-info/top_level.txt
odoo14_addon_l10n_fr_account_tax_unece-14.0.1.1.0.dist-info/RECORD
